aliyunsdkadb/__init__.py
aliyunsdkadb/endpoint.py
aliyunsdkadb/request/__init__.py
aliyunsdkadb/request/v20190315/AllocateClusterPublicConnectionRequest.py
aliyunsdkadb/request/v20190315/ApplyAdviceByIdRequest.py
aliyunsdkadb/request/v20190315/AttachUserENIRequest.py
aliyunsdkadb/request/v20190315/BatchApplyAdviceByIdListRequest.py
aliyunsdkadb/request/v20190315/BindDBResourceGroupWithUserRequest.py
aliyunsdkadb/request/v20190315/BindDBResourcePoolWithUserRequest.py
aliyunsdkadb/request/v20190315/CreateAccountRequest.py
aliyunsdkadb/request/v20190315/CreateDBClusterRequest.py
aliyunsdkadb/request/v20190315/CreateDBResourceGroupRequest.py
aliyunsdkadb/request/v20190315/CreateDBResourcePoolRequest.py
aliyunsdkadb/request/v20190315/CreateElasticPlanRequest.py
aliyunsdkadb/request/v20190315/DeleteAccountRequest.py
aliyunsdkadb/request/v20190315/DeleteDBClusterRequest.py
aliyunsdkadb/request/v20190315/DeleteDBResourceGroupRequest.py
aliyunsdkadb/request/v20190315/DeleteDBResourcePoolRequest.py
aliyunsdkadb/request/v20190315/DeleteElasticPlanRequest.py
aliyunsdkadb/request/v20190315/DescribeAccountsRequest.py
aliyunsdkadb/request/v20190315/DescribeAdviceServiceEnabledRequest.py
aliyunsdkadb/request/v20190315/DescribeAllAccountsRequest.py
aliyunsdkadb/request/v20190315/DescribeAllDataSourceRequest.py
aliyunsdkadb/request/v20190315/DescribeAppliedAdvicesRequest.py
aliyunsdkadb/request/v20190315/DescribeAuditLogConfigRequest.py
aliyunsdkadb/request/v20190315/DescribeAuditLogRecordsRequest.py
aliyunsdkadb/request/v20190315/DescribeAutoRenewAttributeRequest.py
aliyunsdkadb/request/v20190315/DescribeAvailableAdvicesRequest.py
aliyunsdkadb/request/v20190315/DescribeAvailableResourceRequest.py
aliyunsdkadb/request/v20190315/DescribeBackupPolicyRequest.py
aliyunsdkadb/request/v20190315/DescribeBackupsRequest.py
aliyunsdkadb/request/v20190315/DescribeColumnsRequest.py
aliyunsdkadb/request/v20190315/DescribeComputeResourceRequest.py
aliyun_python_sdk_adb-1.1.10.dist-info/LICENSE
aliyun_python_sdk_adb-1.1.10.dist-info/METADATA
aliyun_python_sdk_adb-1.1.10.dist-info/WHEEL
aliyun_python_sdk_adb-1.1.10.dist-info/top_level.txt
aliyun_python_sdk_adb-1.1.10.dist-info/RECORD
